{"이미지 정보":{"이미지 식별자":1060773,"이미지 높이":800,"이미지 파일명":"20191127(중국,샘플)-pt4287k9b(1)-스쿠터(샘플,624)1127얼굴컷-밝기보정해주세요-IMG_6453.JPG","이미지 너비":800},"데이터셋 정보":{"파일 생성일자":"2020-11-12 15:37:06","데이터셋 상세설명":{"렉트좌표":{"아우터":[{"X좌표":417.5,"Y좌표":203.5,"가로":207,"세로":248}],"하의":[{"X좌표":439.5,"Y좌표":365.833,"가로":140,"세로":357}],"원피스":[{}],"상의":[{"X좌표":459.5,"Y좌표":223.167,"가로":32,"세로":154}]},"폴리곤좌표":{"아우터":[{"X좌표37":546.0,"X좌표36":562.0,"X좌표35":593.0,"X좌표34":610.0,"X좌표33":625.0,"X좌표32":616.0,"X좌표31":618.0,"X좌표30":620.0,"Y좌표37":206.0,"Y좌표36":204.0,"X좌표8":428.0,"X좌표9":418.0,"Y좌표33":310.0,"Y좌표32":336.0,"Y좌표35":227.0,"Y좌표34":253.0,"Y좌표31":348.0,"Y좌표30":388.0,"X좌표2":448.0,"X좌표3":435.0,"X좌표1":472.0,"X좌표6":434.0,"X좌표7":426.0,"X좌표4":436.0,"X좌표5":433.0,"Y좌표26":448.0,"Y좌표25":448.0,"Y좌표28":437.0,"Y좌표9":362.0,"Y좌표27":436.0,"Y좌표22":332.0,"Y좌표21":269.0,"Y좌표24":452.0,"Y좌표23":440.0,"Y좌표20":228.0,"X좌표19":543.0,"X좌표18":478.0,"X좌표17":471.0,"X좌표16":466.0,"X좌표15":468.0,"X좌표14":460.0,"X좌표13":451.0,"X좌표12":434.0,"X좌표11":436.0,"Y좌표4":282.0,"X좌표10":430.0,"Y좌표3":263.0,"Y좌표2":240.0,"Y좌표1":224.0,"Y좌표8":338.0,"Y좌표7":325.0,"Y좌표29":428.0,"Y좌표6":313.0,"Y좌표5":296.0,"Y좌표15":330.0,"Y좌표14":382.0,"Y좌표17":261.0,"Y좌표16":292.0,"Y좌표11":398.0,"Y좌표10":380.0,"Y좌표13":441.0,"Y좌표12":436.0,"X좌표29":625.0,"X좌표28":604.0,"X좌표27":577.0,"X좌표26":570.0,"X좌표25":541.0,"X좌표24":514.0,"X좌표23":486.0,"X좌표22":482.0,"X좌표21":490.0,"X좌표20":510.0,"Y좌표19":212.0,"Y좌표18":224.0}],"하의":[{"Y좌표9":723.333,"X좌표19":440.0,"X좌표18":486.0,"X좌표17":541.0,"X좌표16":556.0,"X좌표15":564.0,"X좌표14":576.0,"X좌표13":572.0,"X좌표12":580.0,"X좌표11":575.0,"Y좌표4":604.333,"X좌표10":570.0,"Y좌표3":551.333,"Y좌표2":478.333,"Y좌표1":370.333,"Y좌표8":711.333,"Y좌표7":680.333,"Y좌표6":687.333,"Y좌표5":681.333,"Y좌표15":407.333,"Y좌표14":488.333,"X좌표8":527.0,"Y좌표17":367.333,"X좌표9":542.0,"Y좌표16":367.333,"Y좌표11":697.333,"Y좌표10":721.333,"Y좌표13":529.333,"Y좌표12":617.333,"X좌표2":456.0,"X좌표3":460.0,"X좌표1":449.0,"X좌표6":508.0,"Y좌표19":368.333,"X좌표7":528.0,"Y좌표18":366.333,"X좌표4":466.0,"X좌표5":492.0}],"원피스":[{}],"상의":[{"X좌표8":487.0,"X좌표9":491.0,"Y좌표9":264.667,"Y좌표11":243.667,"Y좌표10":254.667,"Y좌표12":226.667,"X좌표12":481.0,"X좌표11":484.0,"X좌표2":468.0,"Y좌표4":314.667,"X좌표10":492.0,"X좌표3":468.0,"Y좌표3":267.667,"Y좌표2":231.667,"X좌표1":481.0,"Y좌표1":223.667,"X좌표6":482.0,"Y좌표8":287.667,"X좌표7":484.0,"Y좌표7":360.667,"X좌표4":460.0,"Y좌표6":367.667,"X좌표5":468.0,"Y좌표5":377.667}]},"라벨링":{"스타일":[{"스타일":"스트리트"}],"아우터":[{"기장":"노말","색상":"카키","서브색상":"브라운","카테고리":"점퍼","디테일":["퀄팅"],"소매기장":"긴팔","소재":["우븐"],"프린트":["무지"],"넥라인":"노카라","핏":"루즈"}],"하의":[{"기장":"발목","색상":"블루","카테고리":"청바지","소재":["데님"],"프린트":["무지"],"핏":"와이드"}],"원피스":[{}],"상의":[{"색상":"베이지","카테고리":"니트웨어","소매기장":"없음","소재":["니트"],"프린트":["무지"],"넥라인":"브이넥"}]}},"파일 번호":1060773,"파일 이름":"20191127(중국,샘플)-pt4287k9b(1)-스쿠터(샘플,624)1127얼굴컷-밝기보정해주세요-IMG_6453.JPG"}}