{"이미지 정보":{"이미지 식별자":1231927,"이미지 높이":800,"이미지 파일명":"1-(9)-009-276-4,164-19,041-Forme_304_02.jpg","이미지 너비":800},"데이터셋 정보":{"파일 생성일자":"2020-11-19 16:10:50","데이터셋 상세설명":{"렉트좌표":{"아우터":[{"X좌표":286.0,"Y좌표":42.5,"가로":258,"세로":435}],"하의":[{"X좌표":319.0,"Y좌표":295.5,"가로":163,"세로":402}],"원피스":[{}],"상의":[{}]},"폴리곤좌표":{"아우터":[{"X좌표35":446.5,"X좌표34":432.5,"X좌표33":401.5,"X좌표32":389.5,"X좌표31":384.5,"X좌표30":374.5,"X좌표8":516.5,"X좌표9":503.5,"Y좌표33":70.0,"Y좌표32":61.0,"Y좌표35":47.0,"Y좌표34":58.0,"Y좌표31":46.0,"Y좌표30":56.0,"X좌표2":456.5,"X좌표3":511.5,"X좌표1":445.5,"X좌표6":509.5,"X좌표7":512.5,"X좌표4":523.5,"X좌표5":544.5,"Y좌표26":338.0,"Y좌표25":422.0,"Y좌표28":170.0,"Y좌표9":448.0,"Y좌표27":333.0,"Y좌표22":418.0,"Y좌표21":302.0,"Y좌표24":465.0,"Y좌표23":478.0,"Y좌표20":178.0,"X좌표19":401.5,"X좌표18":397.5,"X좌표17":412.5,"X좌표16":414.5,"X좌표15":405.5,"X좌표14":407.5,"X좌표13":472.5,"X좌표12":496.5,"X좌표11":495.5,"Y좌표4":107.0,"X좌표10":501.5,"Y좌표3":69.0,"Y좌표2":51.0,"Y좌표1":43.0,"Y좌표8":448.0,"Y좌표7":413.0,"Y좌표29":70.0,"Y좌표6":340.0,"Y좌표5":332.0,"Y좌표15":446.0,"Y좌표14":478.0,"Y좌표17":344.0,"Y좌표16":388.0,"Y좌표11":431.0,"Y좌표10":432.0,"Y좌표13":476.0,"Y좌표12":464.0,"X좌표29":323.5,"X좌표28":302.5,"X좌표27":286.5,"X좌표26":312.5,"X좌표25":310.5,"X좌표24":316.5,"X좌표23":366.5,"X좌표22":377.5,"X좌표21":392.5,"X좌표20":385.5,"Y좌표19":121.0,"Y좌표18":244.0}],"하의":[{"X좌표8":437.5,"X좌표9":411.5,"X좌표2":403.5,"X좌표3":415.5,"X좌표1":386.5,"X좌표6":474.5,"X좌표7":455.5,"X좌표4":407.5,"X좌표5":482.5,"Y좌표26":296.0,"Y좌표25":348.0,"Y좌표9":681.0,"Y좌표22":473.0,"Y좌표21":590.0,"Y좌표24":418.0,"Y좌표23":476.0,"Y좌표20":693.0,"X좌표19":371.5,"X좌표18":377.5,"X좌표17":388.5,"X좌표16":399.5,"X좌표15":409.5,"X좌표14":405.5,"X좌표13":421.5,"X좌표12":428.5,"X좌표11":428.5,"Y좌표4":474.0,"X좌표10":421.5,"Y좌표3":379.0,"Y좌표2":299.0,"Y좌표1":296.0,"Y좌표8":692.0,"Y좌표7":687.0,"Y좌표6":566.0,"Y좌표5":473.0,"Y좌표15":387.0,"Y좌표14":477.0,"Y좌표17":533.0,"Y좌표16":450.0,"Y좌표11":544.0,"Y좌표10":651.0,"Y좌표13":481.0,"Y좌표12":522.0,"X좌표26":388.5,"X좌표25":386.5,"X좌표24":376.5,"X좌표23":365.5,"X좌표22":335.5,"X좌표21":330.5,"X좌표20":319.5,"Y좌표19":698.0,"Y좌표18":610.0}],"원피스":[{}],"상의":[{}]},"라벨링":{"스타일":[{"스타일":"스트리트"}],"아우터":[{"기장":"하프","색상":"퍼플","카테고리":"점퍼","옷깃":"차이나칼라","디테일":["지퍼","셔링"],"소매기장":"긴팔","소재":["우븐"],"프린트":["무지"],"핏":"타이트"}],"하의":[{"기장":"발목","색상":"네이비","카테고리":"청바지","소재":["데님"],"핏":"스키니"}],"원피스":[{}],"상의":[{}]}},"파일 번호":1231927,"파일 이름":"1-(9)-009-276-4,164-19,041-Forme_304_02.jpg"}}