{"이미지 정보":{"이미지 식별자":194177,"이미지 높이":800,"이미지 파일명":"Dduddu_262_09.jpg","이미지 너비":800},"데이터셋 정보":{"파일 생성일자":"2020-09-07 02:02:43","데이터셋 상세설명":{"렉트좌표":{"아우터":[{}],"하의":[{"X좌표":317.203,"Y좌표":233.5,"가로":209,"세로":455}],"원피스":[{}],"상의":[{"X좌표":311.203,"Y좌표":11.5,"가로":216,"세로":289}]},"폴리곤좌표":{"아우터":[{}],"하의":[{"X좌표8":317.703,"X좌표9":0.0,"Y좌표9":0.0,"Y좌표11":0.0,"Y좌표10":0.0,"X좌표11":0.0,"X좌표2":339.703,"Y좌표4":668.0,"X좌표10":0.0,"X좌표3":408.703,"Y좌표3":689.0,"Y좌표2":537.0,"X좌표1":318.703,"Y좌표1":274.0,"X좌표6":526.703,"Y좌표8":278.0,"X좌표7":345.703,"Y좌표7":234.0,"X좌표4":481.703,"Y좌표6":242.0,"X좌표5":516.703,"Y좌표5":613.0}],"원피스":[{}],"상의":[{"Y좌표9":31.0,"X좌표13":0.0,"X좌표12":0.0,"X좌표11":0.0,"Y좌표4":301.0,"X좌표10":316.703,"Y좌표3":295.0,"Y좌표2":294.0,"Y좌표1":40.0,"Y좌표8":12.0,"Y좌표7":52.0,"Y좌표6":243.0,"Y좌표5":278.0,"X좌표8":462.703,"X좌표9":311.703,"Y좌표11":0.0,"Y좌표10":40.0,"Y좌표13":0.0,"Y좌표12":0.0,"X좌표2":314.703,"X좌표3":385.703,"X좌표1":320.703,"X좌표6":527.703,"X좌표7":462.703,"X좌표4":473.703,"X좌표5":516.703}]},"라벨링":{"스타일":[{"스타일":"오리엔탈","서브스타일":"소피스트케이티드"}],"아우터":[{}],"하의":[{"기장":"발목","색상":"레드","카테고리":"팬츠","소재":["우븐"],"프린트":["무지"],"핏":"스키니"}],"원피스":[{}],"상의":[{"기장":"노멀","색상":"레드","카테고리":"탑","디테일":["스트링"],"소매기장":"민소매","소재":["우븐"],"프린트":["무지"],"넥라인":"브이넥","핏":"노멀"}]}},"파일 번호":194177,"파일 이름":"Dduddu_262_09.jpg"}}