{"이미지 정보":{"이미지 식별자":21162,"이미지 높이":800,"이미지 파일명":"Recipe_133_02.jpg","이미지 너비":800},"데이터셋 정보":{"파일 생성일자":"2020-08-06 08:45:01","데이터셋 상세설명":{"렉트좌표":{"아우터":[{}],"하의":[{"X좌표":164.0,"Y좌표":292.5,"가로":433,"세로":491}],"원피스":[{}],"상의":[{"X좌표":143.0,"Y좌표":8.5,"가로":499,"세로":395}]},"폴리곤좌표":{"아우터":[{}],"하의":[{"X좌표8":597.5,"X좌표9":559.5,"Y좌표9":394.0,"Y좌표11":313.0,"Y좌표10":293.0,"Y좌표12":349.0,"X좌표12":237.5,"X좌표11":320.5,"X좌표2":164.5,"Y좌표4":755.0,"X좌표10":493.5,"X좌표3":192.5,"Y좌표3":680.0,"Y좌표2":469.0,"X좌표1":242.5,"Y좌표1":346.0,"X좌표6":531.5,"Y좌표8":599.0,"X좌표7":592.5,"Y좌표7":759.0,"X좌표4":233.5,"Y좌표6":772.0,"X좌표5":361.5,"Y좌표5":784.0}],"원피스":[{}],"상의":[{"X좌표8":639.5,"X좌표9":582.5,"Y좌표9":28.0,"Y좌표11":13.0,"Y좌표10":9.0,"Y좌표12":53.0,"X좌표12":166.5,"X좌표11":311.5,"X좌표2":143.5,"Y좌표4":395.0,"X좌표10":469.5,"X좌표3":159.5,"Y좌표3":372.0,"Y좌표2":260.0,"X좌표1":163.5,"Y좌표1":52.0,"X좌표6":556.5,"Y좌표8":158.0,"X좌표7":642.5,"Y좌표7":341.0,"X좌표4":291.5,"Y좌표6":404.0,"X좌표5":463.5,"Y좌표5":403.0}]},"라벨링":{"스타일":[{"스타일":"스트리트"}],"아우터":[{}],"하의":[{"기장":"미니","색상":"화이트","카테고리":"팬츠","소재":["우븐"],"프린트":["무지"],"핏":"노멀"}],"원피스":[{}],"상의":[{"기장":"노멀","색상":"와인","카테고리":"티셔츠","소매기장":"반팔","소재":["우븐"],"프린트":["무지","레터링"],"넥라인":"라운드넥","핏":"노멀"}]}},"파일 번호":21162,"파일 이름":"Recipe_133_02.jpg"}}