{"이미지 정보":{"이미지 식별자":313625,"이미지 높이":800,"이미지 파일명":"BLEE_168_11.jpg","이미지 너비":800},"데이터셋 정보":{"파일 생성일자":"2020-09-14 01:47:18","데이터셋 상세설명":{"렉트좌표":{"아우터":[{"X좌표":123.203,"Y좌표":-0.5,"가로":284,"세로":572}],"하의":[{}],"원피스":[{}],"상의":[{}]},"폴리곤좌표":{"아우터":[{"Y좌표9":567.0,"X좌표19":229.703,"X좌표18":294.703,"X좌표17":306.703,"X좌표16":345.703,"X좌표15":381.703,"X좌표14":386.703,"X좌표13":407.703,"X좌표12":375.703,"X좌표11":394.703,"Y좌표4":183.0,"X좌표10":283.703,"Y좌표3":149.0,"Y좌표2":55.0,"Y좌표1":3.0,"Y좌표8":551.0,"Y좌표7":313.0,"Y좌표6":286.0,"Y좌표5":228.0,"Y좌표15":65.0,"Y좌표14":129.0,"X좌표8":147.703,"Y좌표17":10.0,"X좌표9":175.703,"Y좌표16":33.0,"Y좌표11":556.0,"Y좌표10":572.0,"Y좌표13":182.0,"Y좌표12":286.0,"X좌표2":160.703,"X좌표3":140.703,"X좌표1":228.703,"X좌표6":134.703,"Y좌표19":4.0,"X좌표7":146.703,"Y좌표18":0.0,"X좌표4":123.703,"X좌표5":132.703}],"하의":[{}],"원피스":[{}],"상의":[{}]},"라벨링":{"스타일":[{"스타일":"스트리트"}],"아우터":[{"기장":"롱","색상":"그레이","서브색상":"블랙","카테고리":"코트","디테일":["띠"],"소매기장":"긴팔","소재":["울\/캐시미어"],"프린트":["무지"],"핏":"노멀"}],"하의":[{"기장":"발목","카테고리":"청바지","소재":["데님"],"프린트":["무지"],"핏":"스키니"}],"원피스":[{}],"상의":[{}]}},"파일 번호":313625,"파일 이름":"BLEE_168_11.jpg"}}