{"이미지 정보":{"이미지 식별자":575929,"이미지 높이":1066,"이미지 파일명":"2017-07-20 in calli 99001.jpg","이미지 너비":800},"데이터셋 정보":{"파일 생성일자":"2020-10-19 16:52:09","데이터셋 상세설명":{"렉트좌표":{"아우터":[{}],"하의":[{"X좌표":243.5,"Y좌표":506.71,"가로":320,"세로":349}],"원피스":[{}],"상의":[{"X좌표":268.5,"Y좌표":167.437,"가로":279,"세로":405}]},"폴리곤좌표":{"아우터":[{}],"하의":[{"X좌표8":292.0,"X좌표9":299.0,"Y좌표9":546.195,"X좌표2":244.0,"Y좌표4":775.109,"X좌표3":385.0,"Y좌표3":857.078,"Y좌표2":839.085,"X좌표1":299.0,"Y좌표1":550.193,"X좌표6":564.0,"Y좌표8":507.21,"X좌표7":538.0,"Y좌표7":518.205,"X좌표4":412.0,"Y좌표6":826.09,"X좌표5":448.0,"Y좌표5":856.079}],"원피스":[{}],"상의":[{"X좌표8":510.0,"X좌표9":424.0,"Y좌표9":182.931,"Y좌표11":167.937,"Y좌표10":212.92,"Y좌표12":208.922,"X좌표12":287.0,"X좌표11":357.0,"X좌표2":269.0,"Y좌표4":573.785,"X좌표10":412.0,"X좌표3":294.0,"Y좌표3":563.788,"Y좌표2":395.851,"X좌표1":280.0,"Y좌표1":213.92,"X좌표6":503.0,"Y좌표8":212.92,"X좌표7":528.0,"Y좌표7":351.868,"X좌표4":459.0,"Y좌표6":411.845,"X좌표5":548.0,"Y좌표5":545.795}]},"라벨링":{"스타일":[{"스타일":"스트리트","서브스타일":"모던"}],"아우터":[{}],"하의":[{"기장":"미디","색상":"블랙","카테고리":"팬츠","프린트":["무지"],"핏":"와이드"}],"원피스":[{}],"상의":[{"기장":"노멀","색상":"화이트","카테고리":"셔츠","옷깃":"폴로칼라","소매기장":"7부소매","핏":"오버사이즈"}]}},"파일 번호":575929,"파일 이름":"2017-07-20 in calli 99001.jpg"}}