{"이미지 정보":{"이미지 식별자":820308,"이미지 높이":533,"이미지 파일명":"2017_10 촬영원본-반-리ok-없음-13835-13835-lkt_1 (80).jpg","이미지 너비":800},"데이터셋 정보":{"파일 생성일자":"2020-11-04 14:08:10","데이터셋 상세설명":{"렉트좌표":{"아우터":[{"X좌표":328.167,"Y좌표":167.518,"가로":129,"세로":246}],"하의":[{}],"원피스":[{}],"상의":[{}]},"폴리곤좌표":{"아우터":[{"Y좌표9":356.663,"X좌표18":370.667,"X좌표17":386.667,"X좌표16":402.667,"X좌표15":413.667,"X좌표14":429.667,"X좌표13":457.667,"X좌표12":452.667,"X좌표11":454.667,"Y좌표4":292.783,"X좌표10":454.667,"Y좌표3":256.851,"Y좌표2":187.98,"Y좌표1":169.016,"Y좌표8":406.569,"Y좌표7":414.554,"Y좌표6":410.562,"Y좌표5":318.734,"Y좌표15":171.012,"Y좌표14":175.004,"X좌표8":438.667,"Y좌표17":173.008,"X좌표9":444.667,"Y좌표16":173.008,"Y좌표11":290.787,"Y좌표10":319.732,"Y좌표13":230.899,"Y좌표12":266.832,"X좌표2":345.667,"X좌표3":328.667,"X좌표1":372.667,"X좌표6":357.667,"X좌표7":389.667,"Y좌표18":168.018,"X좌표4":333.667,"X좌표5":344.667}],"하의":[{}],"원피스":[{}],"상의":[{}]},"라벨링":{"스타일":[{"스타일":"스트리트","서브스타일":"클래식"}],"아우터":[{"기장":"롱","색상":"오렌지","카테고리":"코트","옷깃":"테일러드칼라","디테일":["단추"],"소매기장":"긴팔","소재":["우븐"],"핏":"루즈"}],"하의":[{}],"원피스":[{}],"상의":[{}]}},"파일 번호":820308,"파일 이름":"2017_10 촬영원본-반-리ok-없음-13835-13835-lkt_1 (80).jpg"}}