{"이미지 정보":{"이미지 식별자":84759,"이미지 높이":800,"이미지 파일명":"LIME_1248_13.jpg","이미지 너비":800},"데이터셋 정보":{"파일 생성일자":"2020-08-10 06:42:13","데이터셋 상세설명":{"렉트좌표":{"아우터":[{"X좌표":299.5,"Y좌표":159.5,"가로":191,"세로":398}],"하의":[{}],"원피스":[{}],"상의":[{}]},"폴리곤좌표":{"아우터":[{"Y좌표9":527.0,"Y좌표22":162.0,"Y좌표21":193.0,"Y좌표24":0.0,"Y좌표23":204.0,"Y좌표20":238.0,"X좌표19":319.0,"X좌표18":322.0,"X좌표17":303.0,"X좌표16":317.0,"X좌표15":309.0,"X좌표14":309.0,"X좌표13":300.0,"X좌표12":338.0,"X좌표11":394.0,"Y좌표4":188.0,"X좌표10":448.0,"Y좌표3":160.0,"Y좌표2":169.0,"Y좌표1":203.0,"Y좌표8":480.0,"Y좌표7":423.0,"Y좌표6":359.0,"Y좌표5":259.0,"Y좌표15":485.0,"Y좌표14":486.0,"X좌표8":486.0,"Y좌표17":400.0,"X좌표9":491.0,"Y좌표16":418.0,"Y좌표11":558.0,"Y좌표10":555.0,"Y좌표13":535.0,"Y좌표12":555.0,"X좌표24":0.0,"X좌표23":385.0,"X좌표22":386.0,"X좌표2":422.0,"X좌표21":334.0,"X좌표3":446.0,"X좌표20":322.0,"X좌표1":390.0,"X좌표6":484.0,"Y좌표19":307.0,"X좌표7":472.0,"Y좌표18":340.0,"X좌표4":481.0,"X좌표5":489.0}],"하의":[{}],"원피스":[{}],"상의":[{}]},"라벨링":{"스타일":[{"스타일":"클래식"}],"아우터":[{"기장":"롱","색상":"카키","카테고리":"패딩","디테일":["단추","띠"],"소매기장":"긴팔","소재":["패딩"],"넥라인":"후드","핏":"노멀"}],"하의":[{}],"원피스":[{}],"상의":[{}]}},"파일 번호":84759,"파일 이름":"LIME_1248_13.jpg"}}