{"이미지 정보":{"이미지 식별자":922771,"이미지 높이":800,"이미지 파일명":"20190827(중국,샘플)-t3377k98(5)-모노코드(샘플,언제나폴라T)0827얼굴컷-jk1760 이미지 같아여-IMG_3276.jpg","이미지 너비":800},"데이터셋 정보":{"파일 생성일자":"2020-11-06 16:01:03","데이터셋 상세설명":{"렉트좌표":{"아우터":[{}],"하의":[{"X좌표":456.5,"Y좌표":357.5,"가로":160,"세로":351}],"원피스":[{}],"상의":[{"X좌표":429.5,"Y좌표":204.5,"가로":186,"세로":234}]},"폴리곤좌표":{"아우터":[{}],"하의":[{"Y좌표9":701.0,"X좌표18":474.0,"X좌표17":457.0,"X좌표16":475.0,"X좌표15":506.0,"X좌표14":519.0,"X좌표13":544.0,"X좌표12":534.0,"X좌표11":535.0,"Y좌표4":404.0,"X좌표10":557.0,"Y좌표3":359.0,"Y좌표2":360.0,"Y좌표1":358.0,"Y좌표8":709.0,"Y좌표7":709.0,"Y좌표6":690.0,"Y좌표5":588.0,"Y좌표15":694.0,"Y좌표14":703.0,"X좌표8":584.0,"Y좌표17":455.0,"X좌표9":562.0,"Y좌표16":694.0,"Y좌표11":462.0,"Y좌표10":546.0,"Y좌표13":698.0,"Y좌표12":582.0,"X좌표2":518.0,"X좌표3":570.0,"X좌표1":474.0,"X좌표6":617.0,"X좌표7":604.0,"Y좌표18":360.0,"X좌표4":594.0,"X좌표5":617.0}],"원피스":[{}],"상의":[{"Y좌표9":376.0,"Y좌표20":210.0,"X좌표19":514.0,"X좌표18":498.0,"X좌표17":486.0,"X좌표16":454.0,"X좌표15":441.0,"X좌표14":434.0,"X좌표13":430.0,"X좌표12":448.0,"X좌표11":469.0,"Y좌표4":439.0,"X좌표10":474.0,"Y좌표3":230.0,"Y좌표2":220.0,"Y좌표1":211.0,"Y좌표8":374.0,"Y좌표7":368.0,"Y좌표6":406.0,"Y좌표5":438.0,"Y좌표15":270.0,"Y좌표14":322.0,"X좌표8":546.0,"Y좌표17":226.0,"X좌표9":477.0,"Y좌표16":238.0,"Y좌표11":369.0,"Y좌표10":318.0,"Y좌표13":341.0,"Y좌표12":369.0,"X좌표2":544.0,"X좌표3":590.0,"X좌표20":538.0,"X좌표1":536.0,"X좌표6":586.0,"Y좌표19":217.0,"X좌표7":574.0,"Y좌표18":205.0,"X좌표4":616.0,"X좌표5":593.0}]},"라벨링":{"스타일":[{"스타일":"스트리트"}],"아우터":[{}],"하의":[{"기장":"발목","색상":"베이지","카테고리":"팬츠","소재":["데님"],"프린트":["무지"],"핏":"와이드"}],"원피스":[{}],"상의":[{"색상":"베이지","카테고리":"니트웨어","소매기장":"긴팔","소재":["니트"],"프린트":["무지"],"넥라인":"터틀넥","핏":"타이트"}]}},"파일 번호":922771,"파일 이름":"20190827(중국,샘플)-t3377k98(5)-모노코드(샘플,언제나폴라T)0827얼굴컷-jk1760 이미지 같아여-IMG_3276.jpg"}}