{"이미지 정보":{"이미지 식별자":974712,"이미지 높이":1049,"이미지 파일명":"6sk1938-1 (255).jpg","이미지 너비":800},"데이터셋 정보":{"파일 생성일자":"2020-11-10 12:37:19","데이터셋 상세설명":{"렉트좌표":{"아우터":[{}],"하의":[{"X좌표":277.5,"Y좌표":273.448,"가로":251,"세로":291}],"원피스":[{}],"상의":[{"X좌표":235.5,"Y좌표":29.4943,"가로":329,"세로":307}]},"폴리곤좌표":{"아우터":[{}],"하의":[{"X좌표8":307.0,"X좌표9":318.0,"Y좌표9":274.948,"Y좌표11":273.948,"Y좌표10":274.948,"X좌표11":504.0,"X좌표2":503.0,"Y좌표4":561.893,"X좌표10":417.0,"X좌표3":529.0,"Y좌표3":441.916,"Y좌표2":313.94,"X좌표1":503.0,"Y좌표1":274.948,"X좌표6":280.0,"Y좌표8":317.939,"X좌표7":278.0,"Y좌표7":421.92,"X좌표4":516.0,"Y좌표6":543.896,"X좌표5":400.0,"Y좌표5":565.892}],"원피스":[{}],"상의":[{"Y좌표9":315.94,"Y좌표22":29.9943,"Y좌표21":56.9891,"Y좌표20":102.98,"X좌표19":385.0,"X좌표18":349.0,"X좌표17":311.0,"X좌표16":280.0,"X좌표15":245.0,"X좌표14":236.0,"X좌표13":318.0,"X좌표12":327.0,"X좌표11":395.0,"Y좌표4":133.974,"X좌표10":464.0,"Y좌표3":72.9861,"Y좌표2":41.992,"Y좌표1":30.9941,"Y좌표8":296.943,"Y좌표7":322.938,"Y좌표6":317.939,"Y좌표5":224.957,"Y좌표15":225.957,"Y좌표14":330.937,"X좌표8":515.0,"Y좌표17":48.9907,"X좌표9":498.0,"Y좌표16":65.9874,"Y좌표11":299.943,"Y좌표10":294.944,"Y좌표13":337.936,"Y좌표12":314.94,"X좌표22":424.0,"X좌표2":488.0,"X좌표21":442.0,"X좌표3":536.0,"X좌표20":416.0,"X좌표1":430.0,"X좌표6":565.0,"Y좌표19":69.9867,"X좌표7":519.0,"Y좌표18":40.9922,"X좌표4":537.0,"X좌표5":552.0}]},"라벨링":{"스타일":[{"스타일":"컨트리","서브스타일":"스트리트"}],"아우터":[{}],"하의":[{"기장":"미니","색상":"브라운","카테고리":"팬츠","디테일":["플리츠"],"소재":["린넨"],"프린트":["무지"],"핏":"와이드"}],"원피스":[{}],"상의":[{"색상":"화이트","서브색상":"카키","카테고리":"셔츠","옷깃":"셔츠칼라","소매기장":"7부소매","소재":["린넨"],"프린트":["체크"],"넥라인":"브이넥","핏":"루즈"}]}},"파일 번호":974712,"파일 이름":"6sk1938-1 (255).jpg"}}