{"이미지 정보":{"이미지 식별자":880319,"이미지 높이":533,"이미지 파일명":"20191002-jk1854k9a(2)-나비(대행,에비뉴패딩)10.7-얼굴컷 사진 셀렉 신경써주시고 제품컷 색상 맞춰서 작업해주세여~-DHP05503.jpg","이미지 너비":800},"데이터셋 정보":{"파일 생성일자":"2020-11-05 16:17:03","데이터셋 상세설명":{"렉트좌표":{"아우터":[{"X좌표":251.5,"Y좌표":78.4704,"가로":251,"세로":353}],"하의":[{}],"원피스":[{}],"상의":[{}]},"폴리곤좌표":{"아우터":[{"X좌표8":252.0,"X좌표9":266.0,"X좌표2":371.0,"X좌표3":391.0,"X좌표1":369.0,"X좌표6":316.0,"X좌표7":265.0,"X좌표4":388.0,"X좌표5":388.0,"Y좌표26":81.9692,"Y좌표25":107.959,"Y좌표9":246.907,"Y좌표22":305.885,"Y좌표21":341.872,"Y좌표24":153.942,"Y좌표23":239.91,"Y좌표20":341.872,"X좌표19":467.0,"X좌표18":468.0,"X좌표17":449.0,"X좌표16":440.0,"X좌표15":441.0,"X좌표14":420.0,"X좌표13":420.0,"X좌표12":368.0,"X좌표11":295.0,"Y좌표4":415.844,"X좌표10":284.0,"Y좌표3":120.955,"Y좌표2":95.964,"Y좌표1":78.9704,"Y좌표8":325.878,"Y좌표7":430.838,"Y좌표6":421.842,"Y좌표5":432.838,"Y좌표15":203.923,"Y좌표14":131.95,"Y좌표17":377.858,"Y좌표16":299.887,"Y좌표11":101.962,"Y좌표10":156.941,"Y좌표13":78.9704,"Y좌표12":78.9704,"X좌표26":421.0,"X좌표25":485.0,"X좌표24":496.0,"X좌표23":487.0,"X좌표22":501.0,"X좌표21":503.0,"X좌표20":468.0,"Y좌표19":364.863,"Y좌표18":405.848}],"하의":[{}],"원피스":[{}],"상의":[{}]},"라벨링":{"스타일":[{"스타일":"젠더리스","서브스타일":"컨트리"}],"아우터":[{"기장":"하프","색상":"블랙","카테고리":"패딩","디테일":["지퍼"],"소매기장":"긴팔","소재":["패딩"],"프린트":["무지"],"넥라인":"라운드넥","핏":"노멀"}],"하의":[{}],"원피스":[{}],"상의":[{}]}},"파일 번호":880319,"파일 이름":"20191002-jk1854k9a(2)-나비(대행,에비뉴패딩)10.7-얼굴컷 사진 셀렉 신경써주시고 제품컷 색상 맞춰서 작업해주세여~-DHP05503.jpg"}}