{"이미지 정보":{"이미지 식별자":33448,"이미지 높이":800,"이미지 파일명":"MAYJ_044_06.jpg","이미지 너비":800},"데이터셋 정보":{"파일 생성일자":"2020-08-07 02:27:03","데이터셋 상세설명":{"렉트좌표":{"아우터":[{"X좌표":347.945,"Y좌표":22.5156,"가로":199,"세로":357}],"하의":[{"X좌표":401.875,"Y좌표":352.516,"가로":143,"세로":314}],"원피스":[{}],"상의":[{}]},"폴리곤좌표":{"아우터":[{"Y좌표9":364.016,"Y좌표20":34.0156,"X좌표19":447.445,"X좌표18":484.445,"X좌표17":494.445,"X좌표16":511.445,"X좌표15":548.445,"X좌표14":542.445,"X좌표13":546.445,"X좌표12":521.445,"X좌표11":534.445,"Y좌표4":263.016,"X좌표10":527.445,"Y좌표3":89.0156,"Y좌표2":23.0156,"Y좌표1":33.0156,"Y좌표8":379.016,"Y좌표7":381.016,"Y좌표6":372.016,"Y좌표5":354.016,"Y좌표15":164.016,"Y좌표14":182.016,"X좌표8":466.445,"Y좌표17":161.016,"X좌표9":481.445,"Y좌표16":159.016,"Y좌표11":321.016,"Y좌표10":342.016,"Y좌표13":212.016,"Y좌표12":233.016,"X좌표2":373.445,"X좌표3":348.445,"X좌표20":414.445,"X좌표1":418.445,"X좌표6":409.445,"Y좌표19":67.0156,"X좌표7":421.445,"Y좌표18":112.016,"X좌표4":371.445,"X좌표5":371.445}],"하의":[{"X좌표8":494.375,"X좌표9":546.375,"Y좌표9":516.016,"Y좌표11":353.016,"Y좌표10":404.016,"X좌표11":507.375,"X좌표2":450.375,"Y좌표4":619.016,"X좌표10":514.375,"X좌표3":450.375,"Y좌표3":554.016,"Y좌표2":491.016,"X좌표1":435.375,"Y좌표1":403.016,"X좌표6":449.375,"Y좌표8":613.016,"X좌표7":474.375,"Y좌표7":668.016,"X좌표4":402.375,"Y좌표6":664.016,"X좌표5":427.375,"Y좌표5":649.016}],"원피스":[{}],"상의":[{}]},"라벨링":{"스타일":[{"스타일":"스트리트"}],"아우터":[{"기장":"하프","색상":"핑크","카테고리":"가디건","소매기장":"긴팔","소재":["저지"],"프린트":["무지"],"핏":"루즈"}],"하의":[{"기장":"발목","색상":"블루","카테고리":"청바지","소재":["데님"],"핏":"스키니"}],"원피스":[{}],"상의":[{"색상":"핑크","소매기장":"긴팔"}]}},"파일 번호":33448,"파일 이름":"MAYJ_044_06.jpg"}}